setup.cfg
setup.py
Wareweb.egg-info/PKG-INFO
Wareweb.egg-info/SOURCES.txt
Wareweb.egg-info/dependency_links.txt
Wareweb.egg-info/entry_points.txt
Wareweb.egg-info/requires.txt
Wareweb.egg-info/top_level.txt
Wareweb.egg-info/zip-safe
docs/index.txt
tests/conftest.py
tests/test_timeinterval.py
tests/test_unpack.py
trunk/setup.cfg
trunk/setup.py
trunk/docs/index.txt
trunk/tests/conftest.py
trunk/tests/test_timeinterval.py
trunk/tests/test_unpack.py
trunk/wareweb/__init__.py
trunk/wareweb/cgifields.py
trunk/wareweb/cookiewriter.py
trunk/wareweb/create_template.py
trunk/wareweb/dispatch.py
trunk/wareweb/event.py
trunk/wareweb/funcs.py
trunk/wareweb/interfaces.py
trunk/wareweb/notify.py
trunk/wareweb/packing.py
trunk/wareweb/servlet.py
trunk/wareweb/servlet_script.py
trunk/wareweb/timeinterval.py
trunk/wareweb/wsgiapp.py
trunk/wareweb/paster_templates/blank_servlet.py_tmpl
trunk/wareweb/paster_templates/wareweb/setup.py_tmpl
trunk/wareweb/paster_templates/wareweb/+package+/__init__.py_tmpl
trunk/wareweb/paster_templates/wareweb/+package+/sitepage.py_tmpl
trunk/wareweb/paster_templates/wareweb/+package+/wsgiapp.py_tmpl
trunk/wareweb/paster_templates/wareweb/+package+/web/__init__.py_tmpl
trunk/wareweb/paster_templates/wareweb/+package+/web/index.py_tmpl
trunk/wareweb/paster_templates/wareweb/docs/devel_config.ini_tmpl
trunk/wareweb/paster_templates/wareweb/tests/conftest.py_tmpl
trunk/wareweb/paster_templates/wareweb/tests/fixture.py_tmpl
trunk/wareweb/paster_templates/wareweb/tests/test_app.py_tmpl
wareweb/__init__.py
wareweb/cgifields.py
wareweb/cookiewriter.py
wareweb/create_template.py
wareweb/dispatch.py
wareweb/event.py
wareweb/funcs.py
wareweb/interfaces.py
wareweb/notify.py
wareweb/packing.py
wareweb/servlet.py
wareweb/servlet_script.py
wareweb/timeinterval.py
wareweb/wsgiapp.py
wareweb/paster_templates/blank_servlet.py_tmpl
wareweb/paster_templates/wareweb/setup.py_tmpl
wareweb/paster_templates/wareweb/+package+/__init__.py_tmpl
wareweb/paster_templates/wareweb/+package+/sitepage.py_tmpl
wareweb/paster_templates/wareweb/+package+/wsgiapp.py_tmpl
wareweb/paster_templates/wareweb/+package+/web/__init__.py_tmpl
wareweb/paster_templates/wareweb/+package+/web/index.py_tmpl
